runtests.py
sql_util/__init__.py
sql_util/aggregates.py
sql_util/apps.py
sql_util/debug.py
sql_util/utils.py
django_sql_utils-0.7.0.dist-info/METADATA
django_sql_utils-0.7.0.dist-info/WHEEL
django_sql_utils-0.7.0.dist-info/licenses/LICENSE
django_sql_utils-0.7.0.dist-info/RECORD
