Metadata-Version: 2.1
Name: django-sql-utils
Version: 0.7.0
Summary: Improved API for aggregating using Subquery
Project-URL: Homepage, https://github.com/martsberger/django-sql-utils
Project-URL: Download, https://github.com/martsberger/django-sql-utils/archive/0.7.0.tar.gz
Author-email: Brad Martsberger <bradley.marts@gmail.com>
License-File: LICENSE
Classifier: License :: OSI Approved :: MIT License
Classifier: Operating System :: OS Independent
Classifier: Programming Language :: Python :: 3
Requires-Python: >=3.8
Requires-Dist: django>=3.2
Requires-Dist: sqlparse
